incenp/__init__.py
incenp/pebble/__init__.py
incenp/pebble/__main__.py
incenp/pebble/cache.py
incenp/pebble/editor.py
incenp/pebble/server.py
incenp/pebble/util.py
incenp.pebble-1.1.1.dist-info/AUTHORS
incenp.pebble-1.1.1.dist-info/COPYING
incenp.pebble-1.1.1.dist-info/METADATA
incenp.pebble-1.1.1.dist-info/WHEEL
incenp.pebble-1.1.1.dist-info/entry_points.txt
incenp.pebble-1.1.1.dist-info/top_level.txt
incenp.pebble-1.1.1.dist-info/RECORD
