Metadata-Version: 2.1
Name: incenp.pebble
Version: 1.1.1
Summary: Command-line Passman client
Home-page: https://git.incenp.org/damien/pebble
Author: Damien Goutte-Gattat
Author-email: dgouttegattat@incenp.org
License: UNKNOWN
Platform: UNKNOWN
Classifier: Development Status :: 5 - Production/Stable
Classifier: Environment :: Console
Classifier: Intended Audience :: End Users/Desktop
Classifier: License :: OSI Approved :: GNU General Public License v3 or later (GPLv3+)
Classifier: Programming Language :: Python :: 3.7
Classifier: Programming Language :: Python :: 3.8
Classifier: Programming Language :: Python :: 3.9
License-File: COPYING
License-File: AUTHORS
Requires-Dist: requests
Requires-Dist: sjcl
Requires-Dist: click
Requires-Dist: click-shell
Provides-Extra: keyring
Requires-Dist: keyring ; extra == 'keyring'
